<?xml version="1.0" encoding="UTF-8"?>
<!DOCTYPE mapper PUBLIC "-//mybatis.org//DTD Mapper 3.0//EN" "http://mybatis.org/dtd/mybatis-3-mapper.dtd">

<mapper namespace="kosa.afnica.backend.db.mapper.CarMapper">
    <!--  Brand 저장  -->
    <insert id="saveBrand" parameterType="brand">
        INSERT INTO BRAND (ID, LOGO, NAME)
        VALUES (#{id}, #{logo}, #{name})
    </insert>

    <!--  모든 Brand 조회  -->
    <select id="findAllBrand" resultType="brand">
        SELECT ID, NAME, LOGO
        FROM BRAND
    </select>

    <!--  CarType 저장  -->
    <insert id="saveCarType" parameterType="carType">
        INSERT INTO CAR_TYPE (ID, NAME, BRAND_ID, LOGO)
        VALUES (#{id}, #{name}, #{brandId}, #{logo})
    </insert>

    <!--  BrandId를 기반으로 모든 CarType 조회  -->
    <select id="findAllCarTypeByBrandId" parameterType="Long" resultType="carType">
        SELECT ID, NAME, BRAND_ID, LOGO
        FROM CAR_TYPE
        WHERE BRAND_ID = #{brandId}
    </select>
</mapper>